[
  {
    "market_id": "1345690",
    "question": "Will Bitcoin dip to $60,000 in February?",
    "direction": "BUY YES",
    "category": "crypto",
    "bin_edge": 0.0537,
    "bin_win_rate": 0.2452,
    "bin_n": 34790,
    "distinct_markets": 230,
    "ci_lower": 0.1925,
    "ci_edge": 0.001,
    "bonferroni_significant": true,
    "market_implied": 0.1665,
    "n_signals": 1,
    "score": 1312.83,
    "hours_to_resolve": 14.0
  },
  {
    "market_id": "1414949",
    "question": "Will the price of Bitcoin be above $60,000 on March 1?",
    "direction": "BUY NO",
    "category": "crypto",
    "bin_edge": 0.1178,
    "bin_win_rate": 0.2483,
    "bin_n": 34644,
    "distinct_markets": 231,
    "ci_lower": 0.1956,
    "ci_edge": 0.0651,
    "bonferroni_significant": false,
    "market_implied": 0.10549999999999993,
    "n_signals": 1,
    "score": 392.02,
    "hours_to_resolve": 14.0
  },
  {
    "market_id": "1414962",
    "question": "Will the price of Bitcoin be above $66,000 on March 1?",
    "direction": "BUY YES",
    "category": "crypto",
    "bin_edge": 0.0802,
    "bin_win_rate": 0.2452,
    "bin_n": 34790,
    "distinct_markets": 230,
    "ci_lower": 0.1925,
    "ci_edge": 0.0275,
    "bonferroni_significant": true,
    "market_implied": 0.14,
    "n_signals": 1,
    "score": 364.15,
    "hours_to_resolve": 14.0
  },
  {
    "market_id": "1414914",
    "question": "Will the price of Bitcoin be between $66,000 and $68,000 on March 1?",
    "direction": "BUY YES",
    "category": "crypto",
    "bin_edge": 0.1152,
    "bin_win_rate": 0.2452,
    "bin_n": 34790,
    "distinct_markets": 230,
    "ci_lower": 0.1925,
    "ci_edge": 0.0625,
    "bonferroni_significant": true,
    "market_implied": 0.10500000000000001,
    "n_signals": 1,
    "score": 234.93,
    "hours_to_resolve": 14.0
  },
  {
    "market_id": "1414460",
    "question": "Lakers vs. Warriors",
    "direction": "BUY YES",
    "category": "sports",
    "bin_edge": 0.0321,
    "bin_win_rate": 0.6721,
    "bin_n": 562539,
    "distinct_markets": 1588,
    "ci_lower": 0.6484,
    "ci_edge": 0.0084,
    "bonferroni_significant": true,
    "market_implied": 0.615,
    "n_signals": 1,
    "score": 179.05,
    "hours_to_resolve": 14.0
  },
  {
    "market_id": "1003711",
    "question": "Will Amy Madigan win Best Supporting Actress in a Motion Picture at the 2026 SAG Awards?",
    "direction": "BUY YES",
    "category": "entertainment",
    "bin_edge": 0.1156,
    "bin_win_rate": 0.6506,
    "bin_n": 57262,
    "distinct_markets": 122,
    "ci_lower": 0.5594,
    "ci_edge": 0.0244,
    "bonferroni_significant": true,
    "market_implied": 0.51,
    "n_signals": 1,
    "score": 174.12,
    "hours_to_resolve": 14.0
  },
  {
    "market_id": "1353473",
    "question": "UFC Fight Night: Macy Chiasson vs. Ailin Perez (Women's Bantamweight, Prelims)",
    "direction": "BUY NO",
    "category": "sports",
    "bin_edge": 0.0459,
    "bin_win_rate": 0.6759,
    "bin_n": 571214,
    "distinct_markets": 1597,
    "ci_lower": 0.6523,
    "ci_edge": 0.0223,
    "bonferroni_significant": true,
    "market_implied": 0.605,
    "n_signals": 1,
    "score": 154.46,
    "hours_to_resolve": 14.0
  },
  {
    "market_id": "1314028",
    "question": "Capitals vs. Canadiens",
    "direction": "BUY NO",
    "category": "sports",
    "bin_edge": 0.0459,
    "bin_win_rate": 0.6759,
    "bin_n": 571214,
    "distinct_markets": 1597,
    "ci_lower": 0.6523,
    "ci_edge": 0.0223,
    "bonferroni_significant": true,
    "market_implied": 0.605,
    "n_signals": 1,
    "score": 139.29,
    "hours_to_resolve": 14.0
  },
  {
    "market_id": "1414909",
    "question": "Will the price of Bitcoin be between $60,000 and $62,000 on March 1?",
    "direction": "BUY YES",
    "category": "crypto",
    "bin_edge": 0.0657,
    "bin_win_rate": 0.2452,
    "bin_n": 34790,
    "distinct_markets": 230,
    "ci_lower": 0.1925,
    "ci_edge": 0.013,
    "bonferroni_significant": true,
    "market_implied": 0.1545,
    "n_signals": 1,
    "score": 117.01,
    "hours_to_resolve": 14.0
  },
  {
    "market_id": "1415051",
    "question": "Will the price of XRP be between $1.30 and $1.40 on March 1?",
    "direction": "BUY YES",
    "category": "other",
    "bin_edge": 0.1178,
    "bin_win_rate": 0.4478,
    "bin_n": 196458,
    "distinct_markets": 702,
    "ci_lower": 0.4109,
    "ci_edge": 0.0809,
    "bonferroni_significant": true,
    "market_implied": 0.30500000000000005,
    "n_signals": 1,
    "score": 105.72,
    "hours_to_resolve": 14.0
  },
  {
    "market_id": "1003635",
    "question": "Will Jessie Buckley win Best Actress in a Motion Picture at the 2026 SAG Awards?",
    "direction": "BUY YES",
    "category": "entertainment",
    "bin_edge": 0.0687,
    "bin_win_rate": 0.8987,
    "bin_n": 236188,
    "distinct_markets": 393,
    "ci_lower": 0.8644,
    "ci_edge": 0.0344,
    "bonferroni_significant": false,
    "market_implied": 0.8049999999999999,
    "n_signals": 1,
    "score": 100.84,
    "hours_to_resolve": 14.0
  },
  {
    "market_id": "1003556",
    "question": "Will \"One Battle After Another\" win Outstanding Performance by a Cast in a Motion Picture at the 32nd Actor Awards?",
    "direction": "BUY YES",
    "category": "other",
    "bin_edge": 0.0828,
    "bin_win_rate": 0.4478,
    "bin_n": 196458,
    "distinct_markets": 702,
    "ci_lower": 0.4109,
    "ci_edge": 0.0459,
    "bonferroni_significant": true,
    "market_implied": 0.34,
    "n_signals": 1,
    "score": 81.33,
    "hours_to_resolve": 14.0
  },
  {
    "market_id": "1299649",
    "question": "Will Tundra Esports win DreamLeague 28?",
    "direction": "BUY YES",
    "category": "other",
    "bin_edge": 0.1178,
    "bin_win_rate": 0.4478,
    "bin_n": 196458,
    "distinct_markets": 702,
    "ci_lower": 0.4109,
    "ci_edge": 0.0809,
    "bonferroni_significant": true,
    "market_implied": 0.305,
    "n_signals": 1,
    "score": 49.06,
    "hours_to_resolve": 14.0
  },
  {
    "market_id": "1419253",
    "question": "Will Bitcoin dip to $58,000 February 23-March 1?",
    "direction": "BUY YES",
    "category": "crypto",
    "bin_edge": 0.0788,
    "bin_win_rate": 0.2328,
    "bin_n": 49600,
    "distinct_markets": 231,
    "ci_lower": 0.1838,
    "ci_edge": 0.0298,
    "bonferroni_significant": true,
    "market_implied": 0.129,
    "n_signals": 1,
    "score": 133.11,
    "hours_to_resolve": 38.0
  },
  {
    "market_id": "1399376",
    "question": "Will \"Scream 7\" Opening Weekend Box Office be greater than 65m?",
    "direction": "BUY YES",
    "category": "entertainment",
    "bin_edge": 0.0405,
    "bin_win_rate": 0.8755,
    "bin_n": 217202,
    "distinct_markets": 449,
    "ci_lower": 0.8415,
    "ci_edge": 0.0065,
    "bonferroni_significant": false,
    "market_implied": 0.81,
    "n_signals": 1,
    "score": 103.82,
    "hours_to_resolve": 38.0
  },
  {
    "market_id": "1454055",
    "question": "S&P 500 (SPX) Opens Up or Down on March 2?",
    "direction": "BUY NO",
    "category": "other",
    "bin_edge": 0.0425,
    "bin_win_rate": 0.9025,
    "bin_n": 288043,
    "distinct_markets": 1005,
    "ci_lower": 0.8826,
    "ci_edge": 0.0226,
    "bonferroni_significant": false,
    "market_implied": 0.835,
    "n_signals": 1,
    "score": 49.05,
    "hours_to_resolve": 38.0
  },
  {
    "market_id": "1419279",
    "question": "Will Solana dip to $70 February 23-March 1?",
    "direction": "BUY YES",
    "category": "crypto",
    "bin_edge": 0.0518,
    "bin_win_rate": 0.2328,
    "bin_n": 49600,
    "distinct_markets": 231,
    "ci_lower": 0.1838,
    "ci_edge": 0.0028,
    "bonferroni_significant": true,
    "market_implied": 0.156,
    "n_signals": 1,
    "score": 43.71,
    "hours_to_resolve": 38.0
  },
  {
    "market_id": "1427145",
    "question": "Kings vs. Lakers",
    "direction": "BUY NO",
    "category": "sports",
    "bin_edge": 0.061,
    "bin_win_rate": 0.921,
    "bin_n": 292197,
    "distinct_markets": 554,
    "ci_lower": 0.8951,
    "ci_edge": 0.0351,
    "bonferroni_significant": false,
    "market_implied": 0.835,
    "n_signals": 1,
    "score": 28.61,
    "hours_to_resolve": 38.0
  },
  {
    "market_id": "1428011",
    "question": "Will the price of Bitcoin be above $64,000 on March 3?",
    "direction": "BUY YES",
    "category": "crypto",
    "bin_edge": 0.1101,
    "bin_win_rate": 0.5951,
    "bin_n": 17899,
    "distinct_markets": 108,
    "ci_lower": 0.4983,
    "ci_edge": 0.0133,
    "bonferroni_significant": true,
    "market_implied": 0.45999999999999996,
    "n_signals": 1,
    "score": 72.31,
    "hours_to_resolve": 62.0
  },
  {
    "market_id": "1348999",
    "question": "Will Jon Bonck be the Republican Nominee for TX-38?",
    "direction": "BUY YES",
    "category": "politics",
    "bin_edge": 0.0422,
    "bin_win_rate": 0.9772,
    "bin_n": 370216,
    "distinct_markets": 294,
    "ci_lower": 0.9517,
    "ci_edge": 0.0167,
    "bonferroni_significant": false,
    "market_implied": 0.91,
    "n_signals": 1,
    "score": 45.88,
    "hours_to_resolve": 62.0
  },
  {
    "market_id": "1405360",
    "question": "Will Elon Musk post 280-299 tweets from February 24 to March 3, 2026?",
    "direction": "BUY NO",
    "category": "other",
    "bin_edge": 0.0275,
    "bin_win_rate": 0.8975,
    "bin_n": 334497,
    "distinct_markets": 1094,
    "ci_lower": 0.8782,
    "ci_edge": 0.0082,
    "bonferroni_significant": false,
    "market_implied": 0.845,
    "n_signals": 1,
    "score": 41.96,
    "hours_to_resolve": 62.0
  },
  {
    "market_id": "1395538",
    "question": "Will James Talarico and John Cornyn be the candidates for the Texas Senate Election?",
    "direction": "BUY NO",
    "category": "politics",
    "bin_edge": 0.0577,
    "bin_win_rate": 0.9977,
    "bin_n": 198576,
    "distinct_markets": 186,
    "ci_lower": 0.9798,
    "ci_edge": 0.0398,
    "bonferroni_significant": false,
    "market_implied": 0.915,
    "n_signals": 1,
    "score": 38.47,
    "hours_to_resolve": 62.0
  },
  {
    "market_id": "1405307",
    "question": "Will Andrew Tate post 100-129 posts from February 24 to March 3, 2026?",
    "direction": "BUY YES",
    "category": "other",
    "bin_edge": 0.06,
    "bin_win_rate": 0.405,
    "bin_n": 148479,
    "distinct_markets": 704,
    "ci_lower": 0.3692,
    "ci_edge": 0.0242,
    "bonferroni_significant": true,
    "market_implied": 0.32,
    "n_signals": 1,
    "score": 34.84,
    "hours_to_resolve": 62.0
  },
  {
    "market_id": "1428027",
    "question": "Will the price of Bitcoin be above $68,000 on March 3?",
    "direction": "BUY YES",
    "category": "crypto",
    "bin_edge": 0.0904,
    "bin_win_rate": 0.2254,
    "bin_n": 63351,
    "distinct_markets": 269,
    "ci_lower": 0.1808,
    "ci_edge": 0.0458,
    "bonferroni_significant": false,
    "market_implied": 0.11,
    "n_signals": 1,
    "score": 33.03,
    "hours_to_resolve": 62.0
  },
  {
    "market_id": "1387720",
    "question": "LoL: HMBLE vs Colossal Gaming (BO5) - LIT Playoffs",
    "direction": "BUY YES",
    "category": "sports",
    "bin_edge": 0.0715,
    "bin_win_rate": 0.9015,
    "bin_n": 256370,
    "distinct_markets": 539,
    "ci_lower": 0.8736,
    "ci_edge": 0.0436,
    "bonferroni_significant": false,
    "market_implied": 0.8049999999999999,
    "n_signals": 1,
    "score": 45.4,
    "hours_to_resolve": 134.0
  },
  {
    "market_id": "1423634",
    "question": "Will Elon Musk post 240-259 tweets from February 27 to March 6, 2026?",
    "direction": "BUY NO",
    "category": "other",
    "bin_edge": 0.0513,
    "bin_win_rate": 0.9773,
    "bin_n": 1131951,
    "distinct_markets": 2246,
    "ci_lower": 0.9703,
    "ci_edge": 0.0443,
    "bonferroni_significant": false,
    "market_implied": 0.901,
    "n_signals": 1,
    "score": 26.91,
    "hours_to_resolve": 134.0
  },
  {
    "market_id": "956347",
    "question": "Will South Africa win the 2026 ICC Men\u2019s T20 World Cup?",
    "direction": "BUY YES",
    "category": "other",
    "bin_edge": 0.1178,
    "bin_win_rate": 0.4478,
    "bin_n": 196458,
    "distinct_markets": 702,
    "ci_lower": 0.4109,
    "ci_edge": 0.0809,
    "bonferroni_significant": true,
    "market_implied": 0.305,
    "n_signals": 1,
    "score": 464.91,
    "hours_to_resolve": 182.0
  },
  {
    "market_id": "956344",
    "question": "Will India win the 2026 ICC Men\u2019s T20 World Cup?",
    "direction": "BUY YES",
    "category": "other",
    "bin_edge": 0.0678,
    "bin_win_rate": 0.4478,
    "bin_n": 196458,
    "distinct_markets": 702,
    "ci_lower": 0.4109,
    "ci_edge": 0.0309,
    "bonferroni_significant": true,
    "market_implied": 0.355,
    "n_signals": 1,
    "score": 305.78,
    "hours_to_resolve": 182.0
  },
  {
    "market_id": "956349",
    "question": "Will New Zealand win the 2026 ICC Men\u2019s T20 World Cup?",
    "direction": "BUY YES",
    "category": "other",
    "bin_edge": 0.0372,
    "bin_win_rate": 0.1757,
    "bin_n": 421232,
    "distinct_markets": 1164,
    "ci_lower": 0.1553,
    "ci_edge": 0.0168,
    "bonferroni_significant": true,
    "market_implied": 0.11349999999999999,
    "n_signals": 1,
    "score": 127.81,
    "hours_to_resolve": 182.0
  },
  {
    "market_id": "1386619",
    "question": "Will the DHS shutdown last 60 days or more?",
    "direction": "BUY NO",
    "category": "other",
    "bin_edge": 0.0675,
    "bin_win_rate": 0.9025,
    "bin_n": 288043,
    "distinct_markets": 1005,
    "ci_lower": 0.8826,
    "ci_edge": 0.0476,
    "bonferroni_significant": false,
    "market_implied": 0.81,
    "n_signals": 1,
    "score": 30.83,
    "hours_to_resolve": 326.0
  },
  {
    "market_id": "614253",
    "question": "Will Stellan Skarsg\u00e5rd win Best Supporting Actor at the 98th Academy Awards?",
    "direction": "BUY NO",
    "category": "entertainment",
    "bin_edge": 0.0553,
    "bin_win_rate": 0.8153,
    "bin_n": 156028,
    "distinct_markets": 344,
    "ci_lower": 0.7694,
    "ci_edge": 0.0094,
    "bonferroni_significant": false,
    "market_implied": 0.735,
    "n_signals": 1,
    "score": 931.6,
    "hours_to_resolve": 350.0
  },
  {
    "market_id": "614008",
    "question": "Will Timoth\u00e9e Chalamet win Best Actor at the 98th Academy Awards?",
    "direction": "BUY YES",
    "category": "entertainment",
    "bin_edge": 0.0832,
    "bin_win_rate": 0.8082,
    "bin_n": 150591,
    "distinct_markets": 347,
    "ci_lower": 0.7621,
    "ci_edge": 0.0371,
    "bonferroni_significant": false,
    "market_implied": 0.7,
    "n_signals": 1,
    "score": 637.15,
    "hours_to_resolve": 350.0
  },
  {
    "market_id": "614355",
    "question": "Will Teyana Taylor win Best Supporting Actress at the 98th Academy Awards?",
    "direction": "BUY NO",
    "category": "entertainment",
    "bin_edge": 0.1122,
    "bin_win_rate": 0.6572,
    "bin_n": 59528,
    "distinct_markets": 128,
    "ci_lower": 0.5705,
    "ci_edge": 0.0255,
    "bonferroni_significant": false,
    "market_implied": 0.52,
    "n_signals": 1,
    "score": 402.91,
    "hours_to_resolve": 350.0
  },
  {
    "market_id": "614361",
    "question": "Will Amy Madigan win Best Supporting Actress at the 98th Academy Awards?",
    "direction": "BUY NO",
    "category": "entertainment",
    "bin_edge": 0.0643,
    "bin_win_rate": 0.8153,
    "bin_n": 156028,
    "distinct_markets": 344,
    "ci_lower": 0.7694,
    "ci_edge": 0.0184,
    "bonferroni_significant": false,
    "market_implied": 0.726,
    "n_signals": 1,
    "score": 318.96,
    "hours_to_resolve": 350.0
  },
  {
    "market_id": "1235861",
    "question": "Will Dominican Republic win the 2026 World Baseball Classic?",
    "direction": "BUY NO",
    "category": "other",
    "bin_edge": 0.0487,
    "bin_win_rate": 0.8937,
    "bin_n": 340981,
    "distinct_markets": 1028,
    "ci_lower": 0.8737,
    "ci_edge": 0.0287,
    "bonferroni_significant": false,
    "market_implied": 0.8200000000000001,
    "n_signals": 1,
    "score": 27.21,
    "hours_to_resolve": 398.0
  },
  {
    "market_id": "1261937",
    "question": "Spread: Grizzlies (-2.5)",
    "direction": "BUY NO",
    "category": "other",
    "bin_edge": 0.0355,
    "bin_win_rate": 0.9805,
    "bin_n": 1536568,
    "distinct_markets": 2484,
    "ci_lower": 0.9745,
    "ci_edge": 0.0295,
    "bonferroni_significant": false,
    "market_implied": 0.92,
    "n_signals": 1,
    "score": 30.97,
    "hours_to_resolve": 422.0
  },
  {
    "market_id": "1011905",
    "question": "Will the Bank of Russia decrease the key rate after the March Meeting?",
    "direction": "BUY NO",
    "category": "other",
    "bin_edge": 0.0799,
    "bin_win_rate": 0.4149,
    "bin_n": 145772,
    "distinct_markets": 695,
    "ci_lower": 0.3783,
    "ci_edge": 0.0433,
    "bonferroni_significant": true,
    "market_implied": 0.31000000000000005,
    "n_signals": 1,
    "score": 36.95,
    "hours_to_resolve": 470.0
  },
  {
    "market_id": "677361",
    "question": "Will Russia capture Kostyantynivka by March 31?",
    "direction": "BUY NO",
    "category": "other",
    "bin_edge": 0.0464,
    "bin_win_rate": 0.7864,
    "bin_n": 232542,
    "distinct_markets": 928,
    "ci_lower": 0.7591,
    "ci_edge": 0.0191,
    "bonferroni_significant": false,
    "market_implied": 0.715,
    "n_signals": 1,
    "score": 178.25,
    "hours_to_resolve": 734.0
  },
  {
    "market_id": "898685",
    "question": "Israel x Hamas Ceasefire Phase II by March 31?",
    "direction": "BUY NO",
    "category": "other",
    "bin_edge": 0.0451,
    "bin_win_rate": 0.9851,
    "bin_n": 1785003,
    "distinct_markets": 2920,
    "ci_lower": 0.9798,
    "ci_edge": 0.0398,
    "bonferroni_significant": false,
    "market_implied": 0.915,
    "n_signals": 1,
    "score": 120.58,
    "hours_to_resolve": 734.0
  },
  {
    "market_id": "1117242",
    "question": "Nothing Ever Happens: Khamenei",
    "direction": "BUY YES",
    "category": "other",
    "bin_edge": 0.0477,
    "bin_win_rate": 0.5727,
    "bin_n": 106999,
    "distinct_markets": 406,
    "ci_lower": 0.5253,
    "ci_edge": 0.0003,
    "bonferroni_significant": true,
    "market_implied": 0.5,
    "n_signals": 1,
    "score": 113.67,
    "hours_to_resolve": 734.0
  },
  {
    "market_id": "1121549",
    "question": "Nothing Ever Happens: MicroStrategy",
    "direction": "BUY YES",
    "category": "other",
    "bin_edge": 0.04,
    "bin_win_rate": 0.98,
    "bin_n": 1553009,
    "distinct_markets": 2509,
    "ci_lower": 0.9738,
    "ci_edge": 0.0338,
    "bonferroni_significant": false,
    "market_implied": 0.915,
    "n_signals": 1,
    "score": 107.36,
    "hours_to_resolve": 734.0
  },
  {
    "market_id": "954518",
    "question": "Will the Slovenian Democratic Party (SDS) win the most seats in the 2026 Slovenian parliamentary election?",
    "direction": "BUY YES",
    "category": "politics",
    "bin_edge": 0.0572,
    "bin_win_rate": 0.9972,
    "bin_n": 115011,
    "distinct_markets": 188,
    "ci_lower": 0.9705,
    "ci_edge": 0.0305,
    "bonferroni_significant": false,
    "market_implied": 0.915,
    "n_signals": 1,
    "score": 46.29,
    "hours_to_resolve": 734.0
  },
  {
    "market_id": "658931",
    "question": "Will Michigan win the 2026 NCAA Tournament?",
    "direction": "BUY NO",
    "category": "other",
    "bin_edge": 0.0575,
    "bin_win_rate": 0.8975,
    "bin_n": 334497,
    "distinct_markets": 1094,
    "ci_lower": 0.8782,
    "ci_edge": 0.0382,
    "bonferroni_significant": false,
    "market_implied": 0.815,
    "n_signals": 1,
    "score": 77.28,
    "hours_to_resolve": 830.0
  },
  {
    "market_id": "658944",
    "question": "Will Duke win the 2026 NCAA Tournament?",
    "direction": "BUY NO",
    "category": "other",
    "bin_edge": 0.0475,
    "bin_win_rate": 0.8975,
    "bin_n": 334497,
    "distinct_markets": 1094,
    "ci_lower": 0.8782,
    "ci_edge": 0.0282,
    "bonferroni_significant": false,
    "market_implied": 0.825,
    "n_signals": 1,
    "score": 35.94,
    "hours_to_resolve": 830.0
  },
  {
    "market_id": "644409",
    "question": "Will the Philadelphia 76ers win more than 43.5 regular season games in 2025\u201326?",
    "direction": "BUY NO",
    "category": "other",
    "bin_edge": 0.0894,
    "bin_win_rate": 0.4149,
    "bin_n": 145772,
    "distinct_markets": 695,
    "ci_lower": 0.3783,
    "ci_edge": 0.0528,
    "bonferroni_significant": true,
    "market_implied": 0.3005,
    "n_signals": 1,
    "score": 147.51,
    "hours_to_resolve": 1022.0
  },
  {
    "market_id": "643832",
    "question": "Will Luka Doncic lead the NBA in points during the 2025\u201326 NBA season?",
    "direction": "BUY YES",
    "category": "sports",
    "bin_edge": 0.0782,
    "bin_win_rate": 0.9132,
    "bin_n": 291985,
    "distinct_markets": 556,
    "ci_lower": 0.8874,
    "ci_edge": 0.0524,
    "bonferroni_significant": false,
    "market_implied": 0.81,
    "n_signals": 1,
    "score": 88.5,
    "hours_to_resolve": 1022.0
  },
  {
    "market_id": "643901",
    "question": "Will Nikola Jokic lead the NBA in rebounds during the 2025\u201326 NBA season?",
    "direction": "BUY YES",
    "category": "sports",
    "bin_edge": 0.0882,
    "bin_win_rate": 0.9132,
    "bin_n": 291985,
    "distinct_markets": 556,
    "ci_lower": 0.8874,
    "ci_edge": 0.0624,
    "bonferroni_significant": false,
    "market_implied": 0.8,
    "n_signals": 1,
    "score": 76.82,
    "hours_to_resolve": 1022.0
  },
  {
    "market_id": "643399",
    "question": "Will the Portland Trail Blazers make the NBA Playoffs?",
    "direction": "BUY NO",
    "category": "sports",
    "bin_edge": 0.0343,
    "bin_win_rate": 0.7843,
    "bin_n": 820221,
    "distinct_markets": 2043,
    "ci_lower": 0.7658,
    "ci_edge": 0.0158,
    "bonferroni_significant": true,
    "market_implied": 0.725,
    "n_signals": 1,
    "score": 66.31,
    "hours_to_resolve": 1022.0
  },
  {
    "market_id": "643397",
    "question": "Will the Philadelphia 76ers make the NBA Playoffs?",
    "direction": "BUY YES",
    "category": "sports",
    "bin_edge": 0.0682,
    "bin_win_rate": 0.9132,
    "bin_n": 291985,
    "distinct_markets": 556,
    "ci_lower": 0.8874,
    "ci_edge": 0.0424,
    "bonferroni_significant": false,
    "market_implied": 0.8200000000000001,
    "n_signals": 1,
    "score": 66.22,
    "hours_to_resolve": 1022.0
  },
  {
    "market_id": "643386",
    "question": "Will the Los Angeles Clippers make the NBA Playoffs?",
    "direction": "BUY NO",
    "category": "sports",
    "bin_edge": 0.0423,
    "bin_win_rate": 0.6723,
    "bin_n": 622452,
    "distinct_markets": 2083,
    "ci_lower": 0.6516,
    "ci_edge": 0.0216,
    "bonferroni_significant": true,
    "market_implied": 0.605,
    "n_signals": 1,
    "score": 63.82,
    "hours_to_resolve": 1022.0
  }
]